{
  "projects": [
    {
      "slug": "el-nido",
      "title": "El Nido",
      "m2": 327,
      "status": "Proyecto",
      "year": 2026,
      "location": "El Nido, Manantiales, San Carlos, Uruguay",
      "credits": {
        "proyecto": "Noreste Arquitectura",
        "equipo": "Catalina Andersch",
        "obra": "Pepe Obras S.L",
        "paisajismo": "Pinos Studio",
        "interiorismo": "",
        "instalaciones": "Carlitos bala",
        "estructura": "Clara Esperon",
        "fotografias": "Belen Capello"
      },
      "visible": true,
      "images": [
        "01.jpg"
      ],
      "videos": [],
      "cover": "01.jpg"
    },
    {
      "slug": "club-buchardo-nuñez",
      "title": "Club Náutico Buchardo Núñez",
      "m2": 12000,
      "status": "Proyecto",
      "year": 2025,
      "location": "Nuñez, Ciudad de Buenos Aires, Argentina",
      "credits": {
        "proyecto": "Noreste Arquitectura",
        "equipo": "Catalina Andersch",
        "obra": "",
        "paisajismo": "",
        "interiorismo": "",
        "instalaciones": "",
        "estructura": "",
        "fotografias": ""
      },
      "images": [
        "01.jpg"
      ],
      "videos": [],
      "cover": "01.jpg",
      "visible": false
    },
    {
      "slug": "triunvirato",
      "title": "Casa en Villa Urquiza",
      "m2": 140,
      "status": "Construido",
      "year": 2025,
      "location": "Villa Urquiza, Ciudad de Buenos Aires, Argentina",
      "credits": {
        "proyecto": "Noreste Arquitectura",
        "equipo": "Catalina Andersch",
        "obra": "Noreste Arquitectura",
        "paisajismo": "",
        "interiorismo": "",
        "instalaciones": "",
        "estructura": "",
        "fotografias": ""
      },
      "visible": true,
      "images": [
        "01.jpg"
      ],
      "videos": [],
      "cover": "01.jpg"
    },
    {
      "slug": "vidt",
      "title": "Vidt",
      "m2": 29,
      "status": "Proyecto",
      "year": 2025,
      "location": "Recoleta, Ciudad de Buenos Aires, Argentina",
      "credits": {
        "proyecto": "Noreste Arquitectura",
        "equipo": null,
        "obra": null,
        "paisajismo": null,
        "interiorismo": null,
        "instalaciones": null,
        "estructura": null,
        "fotografias": null
      },
      "images": [
        "01.jpg"
      ],
      "videos": [],
      "cover": "01.jpg"
    },
    {
      "slug": "vivienda-la-tacuara",
      "title": "La Tacuara",
      "m2": 190,
      "status": "En obra",
      "year": 2026,
      "location": "Cañuelas, Provincia de Buenos Aires, Argentina",
      "credits": {
        "proyecto": "Noreste Arquitectura",
        "equipo": "Catalina Andersch",
        "obra": "Noreste Arquitectura",
        "paisajismo": "Noreste Arquitectura",
        "interiorismo": "Noreste Arquitectura",
        "instalaciones": "Noreste Arquitectura",
        "estructura": "Ing. Claudio Lara",
        "fotografias": null
      },
      "images": [
        "01.jpg"
      ],
      "videos": [],
      "cover": "01.jpg"
    },
    {
      "slug": "casa-belen-maria",
      "title": "Casa Belén María",
      "m2": 160,
      "status": "En obra",
      "year": 2026,
      "location": "Coronel Suárez, Sur de la Provincia de Buenos Aires, Argentina",
      "credits": {
        "proyecto": "Noreste Arquitectura",
        "equipo": "Catalina Andersch",
        "obra": "Noreste Arquitectura",
        "paisajismo": "Noreste Arquitectura",
        "interiorismo": "Noreste Arquitectura",
        "instalaciones": "Noreste Arquitectura",
        "estructura": "Noreste Arquitectura",
        "fotografias": null
      },
      "images": [
        "01.jpg"
      ],
      "videos": [],
      "cover": "01.jpg"
    },
    {
      "slug": "modulo-ff",
      "title": "La Tacuara 02",
      "m2": 120,
      "status": "En obra",
      "year": 2026,
      "location": "Cañuelas, Provincia de Buenos Aires, Argentina",
      "credits": {
        "proyecto": "Josefina Gardey + Noreste Arquitectura",
        "equipo": null,
        "obra": "Noreste Arquitectura",
        "paisajismo": "Noreste Arquitectura",
        "interiorismo": "Noreste Arquitectura",
        "instalaciones": "Noreste Arquitectura",
        "estructura": "Noreste Arquitectura",
        "fotografias": null
      },
      "images": [
        "01.jpg"
      ],
      "videos": [],
      "cover": "01.jpg"
    },
    {
      "slug": "hipico-la-leyenda",
      "title": "Hípico La Leyenda",
      "m2": 120000,
      "status": "En obra",
      "year": 2026,
      "location": "Pilar, Provincia de Buenos Aires, Argentina",
      "credits": {
        "proyecto": "Noreste Arquitectura",
        "equipo": null,
        "obra": null,
        "paisajismo": null,
        "interiorismo": null,
        "instalaciones": null,
        "estructura": null,
        "fotografias": null
      },
      "images": [
        "01.jpg"
      ],
      "videos": [],
      "cover": "01.jpg"
    },
    {
      "slug": "el-metejon",
      "title": "Sector Ecuestre El Metejón",
      "m2": 4000,
      "status": "En obra",
      "year": 2025,
      "location": "Alejandro Petión, Provincia de Buenos Aires, Argentina",
      "credits": {
        "proyecto": "Noreste Arquitectura",
        "equipo": "Catalina Andersch",
        "obra": null,
        "paisajismo": null,
        "interiorismo": null,
        "instalaciones": null,
        "estructura": null,
        "fotografias": null
      },
      "images": [
        "01.jpg"
      ],
      "videos": [],
      "cover": "01.jpg"
    },
    {
      "slug": "caballerizas",
      "title": "Caballerizas",
      "m2": 2800,
      "status": "Construido",
      "year": 2025,
      "location": "La Dolfina Polo Club, Provincia de Buenos Aires, Argentina",
      "credits": {
        "proyecto": "Josefina Gardey + Noreste Arquitectura",
        "equipo": "",
        "obra": "",
        "paisajismo": "",
        "interiorismo": "",
        "instalaciones": "",
        "estructura": "",
        "fotografias": ""
      },
      "visible": true,
      "images": [
        "01.jpg"
      ],
      "videos": [],
      "cover": "01.jpg"
    },
    {
      "slug": "reforma-vedia",
      "title": "Vedia",
      "m2": 70,
      "status": "Construido",
      "year": 2024,
      "location": "Saavedra, Ciudad de Buenos Aires, Argentina",
      "credits": {
        "proyecto": "Noreste Arquitectura",
        "equipo": "",
        "obra": "Noreste Arquitectura",
        "paisajismo": "",
        "interiorismo": "",
        "instalaciones": "",
        "estructura": "",
        "fotografias": ""
      },
      "visible": true,
      "images": [
        "01.jpg"
      ],
      "videos": [],
      "cover": "01.jpg"
    },
    {
      "slug": "caballerizas-poroto",
      "title": "Caballerizas La Dolfina",
      "m2": 140,
      "status": "Construido",
      "year": 2025,
      "location": "La Dolfina Polo Club, Provincia de Buenos Aires, Argentina",
      "credits": {
        "proyecto": "Noreste Arquitectura",
        "equipo": "Catalina Andersch",
        "obra": "Noreste Arquitectura",
        "paisajismo": "",
        "interiorismo": "Noreste Arquitectura",
        "instalaciones": "",
        "estructura": "",
        "fotografias": ""
      },
      "visible": true,
      "images": [
        "01.jpg"
      ],
      "videos": [],
      "cover": "01.jpg"
    },
    {
      "slug": "la-martona",
      "title": "La Martona",
      "m2": 200,
      "status": "Construido",
      "year": 2025,
      "location": "Cañuelas, Provincia de Buenos Aires, Argentina",
      "credits": {
        "proyecto": "Noreste Arquitectura",
        "equipo": "Catalina Andersch",
        "obra": "Noreste Arquitectura",
        "paisajismo": "",
        "interiorismo": "Noreste Arquitectura",
        "instalaciones": "",
        "estructura": "",
        "fotografias": ""
      },
      "visible": true,
      "images": [
        "P1451010.webp",
        "P1451048.webp",
        "P1451553.webp",
        "P1451542.webp",
        "P1451558.webp",
        "P1451055.webp",
        "P1451036.webp",
        "P1451050.webp",
        "P1451536.webp",
        "P1451540.webp",
        "P1451495.webp",
        "P1451479.webp",
        "P1451505.webp",
        "P1451469.webp",
        "P1451450.webp",
        "P1451432.webp",
        "P1451419.webp",
        "P1451407.webp",
        "P1451370.webp",
        "P1451311.webp",
        "P1451303.webp",
        "P1451288.webp",
        "P1451278.webp",
        "P1451261.webp",
        "P1451216.webp",
        "P1451184.webp",
        "P1451174.webp",
        "P1451155.webp",
        "P1451124.webp",
        "P1451112.webp",
        "P1451072.webp"
      ],
      "videos": [],
      "cover": "P1451010.webp"
    },
    {
      "slug": "puesto-el-mate",
      "title": "El Mate",
      "m2": 112,
      "status": "Construido",
      "year": 2024,
      "location": "San Antonio de Areco, Provincia de Buenos Aires, Argentina",
      "credits": {
        "proyecto": "Noreste Arquitectura",
        "equipo": "",
        "obra": "",
        "paisajismo": "",
        "interiorismo": "",
        "instalaciones": "",
        "estructura": "",
        "fotografias": ""
      },
      "visible": true,
      "images": [
        "01.jpg"
      ],
      "videos": [],
      "cover": "01.jpg"
    },
    {
      "slug": "casa-mia",
      "title": "La Martona 02",
      "m2": 140,
      "status": "Construido",
      "year": 2025,
      "location": "Cañuelas, Provincia de Buenos Aires, Argentina",
      "credits": {
        "proyecto": "Josefina Gardey + Noreste Arquitectura",
        "equipo": "",
        "obra": "",
        "paisajismo": "",
        "interiorismo": "",
        "instalaciones": "",
        "estructura": "",
        "fotografias": ""
      },
      "visible": true,
      "images": [
        "01.jpg"
      ],
      "videos": [],
      "cover": "01.jpg"
    }
  ]
}